container_data_collector/__init__.py
container_data_collector/collector.py
container_data_collector/common_typevars.py
container_data_collector/context.py
container_data_collector/nodes.py
container_data_collector/query.py
container_data_collector/vector_partial.py
container_data_collector-0.1.0.dist-info/LICENSE
container_data_collector-0.1.0.dist-info/METADATA
container_data_collector-0.1.0.dist-info/WHEEL
container_data_collector-0.1.0.dist-info/RECORD
