Metadata-Version: 2.1
Name: container-data-collector
Version: 0.1.0
Summary: Collecting and grouping data from various containers
Home-page: https://github.com/hmnhbfw/container-data-collector
License: MIT
Author: Pavel Tsayukov
Author-email: p.tsayukov@gmail.com
Requires-Python: >=3.11,<4.0
Classifier: Development Status :: 1 - Planning
Classifier: License :: OSI Approved :: MIT License
Classifier: Operating System :: OS Independent
Classifier: Programming Language :: Python :: 3
Classifier: Programming Language :: Python :: 3.11
Classifier: Programming Language :: Python :: 3.12
Project-URL: Bug Tracker, https://github.com/hmnhbfw/container-data-collector/issues
Project-URL: Documentation, https://github.com/hmnhbfw/container-data-collector#readme
Project-URL: Repository, https://github.com/hmnhbfw/container-data-collector
